{
    "v": 1,
    "db_id": "mister_cloud_saves",
    "timestamp": 1767818412,
    "files": {
        "Scripts/cloud_saves.sh": {
            "size": 12232,
            "hash": "3c2b84d40491db14f8ed84e243458c5d",
            "url": "https://raw.githubusercontent.com/bleach86/mister_cloud_saves/refs/heads/main/scripts/cloud_saves.sh",
            "tags": [
                1
            ]
        },
        "cloud_saves/updates/client.tar.xz": {
            "size": 2752268,
            "hash": "37b51e8d697e230bde6d8ed5fda9bd00",
            "url": "https://github.com/bleach86/mister_cloud_saves/releases/download/v1.2.1/client.tar.xz",
            "reboot": true,
            "tags": [
                0
            ]
        }
    },
    "folders": {
        "Scripts": {},
        "cloud_saves": {},
        "cloud_saves/updates": {}
    },
    "tags_dictionary": {
        "cloudsaves": 0,
        "scripts": 1
    }
}